octo_pipeline_python/backends/ansible/__init__.py
octo_pipeline_python/backends/ansible/ansible_backend.py
octo_pipeline_python/backends/ansible/actions/__init__.py
octo_pipeline_python/backends/ansible/actions/ansible_lint_check.py
octo_pipeline_python/backends/ansible/actions/ansible_play.py
octo_pipeline_python/backends/ansible/models/__init__.py
octo_pipeline_python/backends/ansible/models/ansible_model.py
octo_pipeline_backend_ansible_python-1.3.2.dist-info/LICENSE.txt
octo_pipeline_backend_ansible_python-1.3.2.dist-info/METADATA
octo_pipeline_backend_ansible_python-1.3.2.dist-info/README.md
octo_pipeline_backend_ansible_python-1.3.2.dist-info/WHEEL
octo_pipeline_backend_ansible_python-1.3.2.dist-info/top_level.txt
octo_pipeline_backend_ansible_python-1.3.2.dist-info/RECORD
